{
  "indexes": [
    {
      "collectionGroup": "cuestionarios_cliente",
      "queryScope": "COLLECTION",
      "fields": [
        { "fieldPath": "estado", "order": "ASCENDING" },
        { "fieldPath": "creadoEn", "order": "DESCENDING" }
      ]
    },
    {
      "collectionGroup": "cuestionarios_cliente",
      "queryScope": "COLLECTION",
      "fields": [
        { "fieldPath": "estado", "order": "ASCENDING" },
        { "fieldPath": "actualizadoEn", "order": "DESCENDING" }
      ]
    }
  ]
}
